slurminade/__init__.py
slurminade/bundling.py
slurminade/check.py
slurminade/conf.py
slurminade/dispatcher.py
slurminade/execute.py
slurminade/execute_cmds.py
slurminade/function.py
slurminade/function_call.py
slurminade/function_map.py
slurminade/guard.py
slurminade/job_reference.py
slurminade/node_setup.py
slurminade/options.py
slurminade-1.1.2.dist-info/LICENSE
slurminade-1.1.2.dist-info/METADATA
slurminade-1.1.2.dist-info/WHEEL
slurminade-1.1.2.dist-info/top_level.txt
slurminade-1.1.2.dist-info/RECORD
