Metadata-Version: 2.1
Name: slurminade
Version: 1.1.2
Summary: A decorator-based slurm runner.
Author-email: "TU Braunschweig, IBR, Algorithms Group (Dominik Krupke)" <krupke@ibr.cs.tu-bs.de>
Project-URL: Homepage, https://github.com/d-krupke/slurminade
Project-URL: Issues, https://github.com/d-krupke/slurminade/issues
Keywords: slurm
Classifier: Programming Language :: Python :: 3
Classifier: License :: OSI Approved :: MIT License
Classifier: Development Status :: 3 - Alpha
Requires-Python: >=3.8
License-File: LICENSE
Requires-Dist: simple-slurm >=0.2.6
Requires-Dist: click
